porcodio/__init__.py
porcodio/ascii_list.py
porcodio/porcodio.py
tests/__init__.py
tests/test_get_porcodio.py
porcodio-1.0.0.dist-info/LICENSE
porcodio-1.0.0.dist-info/METADATA
porcodio-1.0.0.dist-info/WHEEL
porcodio-1.0.0.dist-info/top_level.txt
porcodio-1.0.0.dist-info/RECORD
