Metadata-Version: 2.1
Name: porcodio
Version: 1.0.0
Summary: A random "porcodio" ascii art generator.
Home-page: https://github.com/BranchScope/porcodio
Author: BranchScope
Author-email: rocco4064@gmail.com
License: UNKNOWN
Platform: UNKNOWN
Classifier: Programming Language :: Python :: 3
Classifier: License :: OSI Approved :: MIT License
Classifier: Operating System :: OS Independent
Requires-Python: >=3.6
License-File: LICENSE
